{
  "btcPrice": 68006.0,
  "priceChange24h": -2.53,
  "fomoIndex": 12,
  "aiCommentCN": "跌的时候想抄底，抄完还在跌",
  "aiCommentEN": "Fear of missing out turns to fear of losing more",
  "lastUpdated": 1772887122.115422,
  "forexRates": {
    "CNY": 6.9047,
    "EUR": 0.86498,
    "GBP": 0.74987
  },
  "historyYesterday": 18,
  "historyLastWeek": 11,
  "historyLastMonth": 12,
  "aiSummaryCN": "【技术观点】\n比特币短期走势仍然偏弱。\n【关键位置】\n当前支撑位：65,000 美元，阻力位：70,000 美元。\n【走势推演】\n短期内可能继续震荡调整。\n【一句提醒】\n操作时应谨慎控风险。",
  "aiSummaryEN": "[Today's View]\nBitcoin's short-term trend remains weak.\n[Key Drivers]\nCurrent support: $65,000, resistance: $70,000.\n[Outlook]\nExpected to continue fluctuating in the short term.\n[Reminder]\nBe cautious and control risk when operating.",
  "aiSummaryUpdated": 1772878781.043309
}