{
  "btcPrice": 70540.0,
  "priceChange24h": -1.01,
  "fomoIndex": 12,
  "aiCommentCN": "行情没动，散户心跳加速。",
  "aiCommentEN": "Market stays calm, hearts of investors race.",
  "lastUpdated": 1774081681.549907,
  "forexRates": {
    "CNY": 6.8943,
    "EUR": 0.86543,
    "GBP": 0.74806
  },
  "historyYesterday": 11,
  "historyLastWeek": 16,
  "historyLastMonth": 9,
  "aiSummaryCN": "【周期判断】\n当前所处周期阶段为牛市周期。\n【当前阶段】\n当前阶段特征为市场调整，投资者情绪低落，BTC价格小幅波动。\n【未来可能走势】\n周期视角下的展望是，BTC价格将继续上涨，但短期内可能会有波动。\n【一句提醒】\n风险或操作提醒：投资者应保持谨慎，做好风险管理。",
  "aiSummaryEN": "[Today's View]\nWe are currently in a bull market cycle.\n[Key Drivers]\nThe current stage is characterized by market adjustment, low investor sentiment, and minor BTC price fluctuations.\n[Outlook]\nFrom a cyclical perspective, the outlook is that the BTC price will continue to rise, but may fluctuate in the short term.\n[Reminder]\nReminder: Investors should remain cautious and manage risks properly.",
  "aiSummaryUpdated": 1774065748.152587
}